pykemon2
