Metadata-Version: 1.0
Name: pykemon2.0
Version: 1.0.3
Summary: A Python wrapper for PokeAPI
Home-page: https://github.com/justmaffie/pykemon2.0
Author: JustMaffie
Author-email: jorivanee@hotmail.com
License: BSD
Keywords: pykemon
Platform: UNKNOWN
